unifiles/__init__.py
unifiles/excel.py
unifiles/exceptions.py
unifiles/pdf.py
unifiles/sqlite.py
unifiles/word.py
unifiles-0.3.1.dist-info/licenses/LICENSE
unifiles-0.3.1.dist-info/METADATA
unifiles-0.3.1.dist-info/WHEEL
unifiles-0.3.1.dist-info/top_level.txt
unifiles-0.3.1.dist-info/RECORD
