Metadata-Version: 2.4
Name: unifiles
Version: 0.3.1
Summary: 统一的文件操作库，提供跨文件类型的统一接口
Author-email: Asheng <w62745@qq.com>
License-Expression: MIT
Project-URL: Homepage, https://github.com/Asheng008/unifiles
Project-URL: Documentation, https://github.com/Asheng008/unifiles
Project-URL: Repository, https://github.com/Asheng008/unifiles
Project-URL: Issues, https://github.com/Asheng008/unifiles/issues
Keywords: file,excel,pdf,word,sqlite,data-processing
Classifier: Development Status :: 3 - Alpha
Classifier: Intended Audience :: Developers
Classifier: Programming Language :: Python :: 3
Classifier: Programming Language :: Python :: 3.10
Classifier: Programming Language :: Python :: 3.11
Classifier: Programming Language :: Python :: 3.12
Classifier: Topic :: Software Development :: Libraries :: Python Modules
Classifier: Topic :: Utilities
Requires-Python: >=3.10
License-File: LICENSE
Requires-Dist: pandas>=2.0.0
Requires-Dist: openpyxl>=3.1.0
Requires-Dist: pypdf>=3.0.0
Requires-Dist: python-docx>=1.0.0
Provides-Extra: dev
Requires-Dist: pytest>=7.0.0; extra == "dev"
Requires-Dist: pytest-cov>=4.0.0; extra == "dev"
Requires-Dist: black>=23.0.0; extra == "dev"
Requires-Dist: mypy>=1.0.0; extra == "dev"
Requires-Dist: pre-commit>=3.0.0; extra == "dev"
Requires-Dist: tomli>=2.0.0; extra == "dev"
Dynamic: license-file
